blitzcoder/__init__.py
blitzcoder/cli/__init__.py
blitzcoder/cli/cli_coder.py
blitzcoder-1.0.19.dist-info/licenses/LICENSE
main/__init__.py
main/graphapi.py
blitzcoder-1.0.19.dist-info/METADATA
blitzcoder-1.0.19.dist-info/WHEEL
blitzcoder-1.0.19.dist-info/entry_points.txt
blitzcoder-1.0.19.dist-info/top_level.txt
blitzcoder-1.0.19.dist-info/RECORD
