Metadata-Version: 2.4
Name: blitzcoder
Version: 1.0.19
Summary: AI-powered development assistant for code generation, refactoring, and project management
Home-page: https://github.com/Raghu6798/Blitz_Coder
Author: BlitzCoder Team
Author-email: BlitzCoder Team <raghunandanerukulla@gmail.com>
Maintainer-email: Raghu Nandan Erukulla <raghunandanerukulla@gmail.com>
License: MIT
Project-URL: Homepage, https://github.com/Raghu6798/BlitzCoder
Project-URL: Repository, https://github.com/Raghu6798/BlitzCoder
Project-URL: Documentation, https://github.com/Raghu6798/BlitzCoder#readme
Project-URL: Bug Tracker, https://github.com/Raghu6798/BlitzCoder/issues
Keywords: ai,code-generation,development,assistant,cli
Classifier: Development Status :: 4 - Beta
Classifier: Intended Audience :: Developers
Classifier: License :: OSI Approved :: MIT License
Classifier: Operating System :: OS Independent
Classifier: Programming Language :: Python :: 3
Classifier: Programming Language :: Python :: 3.9
Classifier: Programming Language :: Python :: 3.10
Classifier: Programming Language :: Python :: 3.11
Classifier: Programming Language :: Python :: 3.12
Classifier: Topic :: Software Development :: Libraries :: Python Modules
Classifier: Topic :: Software Development :: Code Generators
Requires-Python: >=3.9
License-File: LICENSE
Requires-Dist: python-dotenv>=0.0.1
Requires-Dist: langgraph>=0.4.9
Requires-Dist: langchain-groq>=0.3.4
Requires-Dist: langchain-sambanova>=0.1.5
Requires-Dist: langchain>=0.3.26
Requires-Dist: loguru>=0.7.3
Requires-Dist: langchain-google-genai>=2.1.5
Requires-Dist: mem0ai>=0.1.111
Requires-Dist: click>=8.1.8
Requires-Dist: click-help-colors>=0.9.4
Requires-Dist: rich>=14.0.0
Requires-Dist: langfuse>=3.0.5
Requires-Dist: langchain-huggingface>=0.3.0
Requires-Dist: huggingface-hub>=0.33.1
Requires-Dist: sentence-transformers>=4.1.0
Requires-Dist: e2b-code-interpreter>=1.5.2
Provides-Extra: dev
Requires-Dist: pytest>=7.0.0; extra == "dev"
Requires-Dist: pytest-cov>=4.0.0; extra == "dev"
Requires-Dist: black>=22.0.0; extra == "dev"
Requires-Dist: isort>=5.0.0; extra == "dev"
Requires-Dist: flake8>=5.0.0; extra == "dev"
Requires-Dist: mypy>=1.0.0; extra == "dev"
Dynamic: author
Dynamic: home-page
Dynamic: license-file
Dynamic: requires-python
